setup.py
yash_gaussian_binomial_distributions/Binomialdistribution.py
yash_gaussian_binomial_distributions/Gaussiandistribution.py
yash_gaussian_binomial_distributions/Generaldistribution.py
yash_gaussian_binomial_distributions/__init__.py
yash_gaussian_binomial_distributions.egg-info/PKG-INFO
yash_gaussian_binomial_distributions.egg-info/SOURCES.txt
yash_gaussian_binomial_distributions.egg-info/dependency_links.txt
yash_gaussian_binomial_distributions.egg-info/not-zip-safe
yash_gaussian_binomial_distributions.egg-info/top_level.txt