Metadata-Version: 1.0
Name: yash-gaussian-binomial-distributions
Version: 0.1
Summary: Gaussian and Binomial distributions
Home-page: UNKNOWN
Author: Yasaswi Vedula
Author-email: thisisa@test.com
License: UNKNOWN
Platform: UNKNOWN
